outlier_101703572/__init__.py
outlier_101703572/outlier_101703572.py
outlier_101703572-0.0.1.dist-info/LICENSE
outlier_101703572-0.0.1.dist-info/METADATA
outlier_101703572-0.0.1.dist-info/WHEEL
outlier_101703572-0.0.1.dist-info/entry_points.txt
outlier_101703572-0.0.1.dist-info/top_level.txt
outlier_101703572-0.0.1.dist-info/RECORD
