Metadata-Version: 2.1
Name: outlier-101703572
Version: 0.0.1
Summary: Python package to remove outliers from csv file(row removal)
Home-page: https://github.com/sunvir72
Author: Sunvir Singh
Author-email: sunvirsingh72@gmail.com
License: MIT
Platform: UNKNOWN
Classifier: License :: OSI Approved :: MIT License
Classifier: Programming Language :: Python :: 3
Classifier: Programming Language :: Python :: 3.7
